event_portal/__init__.py
event_portal/_base_client.py
event_portal/_client.py
event_portal/_compat.py
event_portal/_constants.py
event_portal/_exceptions.py
event_portal/_files.py
event_portal/_models.py
event_portal/_qs.py
event_portal/_resource.py
event_portal/_response.py
event_portal/_streaming.py
event_portal/_types.py
event_portal/_version.py
event_portal/py.typed
event_portal/_utils/__init__.py
event_portal/_utils/_logs.py
event_portal/_utils/_proxy.py
event_portal/_utils/_reflection.py
event_portal/_utils/_streams.py
event_portal/_utils/_sync.py
event_portal/_utils/_transform.py
event_portal/_utils/_typing.py
event_portal/_utils/_utils.py
event_portal/lib/.keep
event_portal/resources/__init__.py
event_portal/resources/api/__init__.py
event_portal/resources/api/api.py
event_portal/resources/api/v2/__init__.py
event_portal/resources/api/v2/v2.py
event_portal/resources/api/v2/architecture/__init__.py
event_portal/resources/api/v2/architecture/about.py
event_portal/resources/api/v2/architecture/applications.py
event_portal/resources/api/v2/architecture/architecture.py
event_portal/resources/api/v2/architecture/change_application_domain_operations.py
event_portal/resources/api/v2/architecture/configuration_types.py
event_portal/resources/api/v2/architecture/consumers.py
event_portal/resources/api/v2/architecture/custom_attribute_definitions.py
event_portal/resources/api/v2/architecture/enum_versions.py
event_portal/resources/api/v2/architecture/enums.py
event_portal/resources/api/v2/architecture/event_access_requests.py
event_portal/resources/api/v2/architecture/event_access_reviews.py
event_portal/resources/api/v2/architecture/event_api_products.py
event_portal/resources/api/v2/architecture/event_apis.py
event_portal/resources/api/v2/architecture/event_versions.py
event_portal/resources/api/v2/architecture/events.py
event_portal/resources/api/v2/architecture/schema_versions.py
event_portal/resources/api/v2/architecture/schemas.py
event_portal-1.0.0.dist-info/METADATA
event_portal-1.0.0.dist-info/WHEEL
event_portal-1.0.0.dist-info/licenses/LICENSE
event_portal-1.0.0.dist-info/RECORD
